{
  "schema_version": "0.1",
  "review_mode": "initial",
  "review_level": "low",
  "blocked": false,
  "readiness": {
    "implementation_ready": true,
    "criteria": {
      "review_level": "low",
      "ready": {
        "critical": 0,
        "major_max": 0,
        "minor_max": 0
      },
      "not_ready": "requires no Critical findings; Major and Minor findings are warnings in low mode.",
      "ready_with_warnings": {
        "critical": 0,
        "major_max": null,
        "minor_max": null,
        "note": "Major and Minor findings are warnings in low mode."
      }
    },
    "status": "ready_with_warnings"
  },
  "summary": {
    "critical": 0,
    "major": 0,
    "minor": 1
  },
  "issues": [
    {
      "severity": "Minor",
      "title": "No obvious readiness triggers found",
      "description": "The documents passed the built-in heuristic checks, but this is not a security review.",
      "impact": "Subtle domain-specific bugs may still exist.",
      "fix": "Run the strict SpecGuard Review prompt with a model and add human review before implementation."
    }
  ],
  "input": {
    "artifact_count": 3,
    "total_characters": 5264,
    "discovery_characters": 2431,
    "spec_characters": 854,
    "technical_design_characters": 1979,
    "artifacts": [
      {
        "path": "discovery.md",
        "characters": 2431
      },
      {
        "path": "spec.md",
        "characters": 854
      },
      {
        "path": "technical-design.md",
        "characters": 1979
      }
    ]
  },
  "prompt_mode": "Readiness policy for low review level: NOT_READY only when Critical>=1. READY when Critical=0 and there are no Major or Minor warnings. READY_WITH_WARNINGS when Critical=0 and Major or Minor warnings exist. Major and Minor findings are warning-level findings and do not block implementation in low mode.",
  "review_input": {
    "mode": "heuristic",
    "review_level": "low",
    "artifact_count": 3,
    "total_characters": 5264,
    "artifacts": [
      {
        "path": "discovery.md",
        "characters": 2431
      },
      {
        "path": "spec.md",
        "characters": 854
      },
      {
        "path": "technical-design.md",
        "characters": 1979
      }
    ]
  }
}
